jamesbot/__init__.py
jamesbot/bloomberg_api.py
jamesbot/data_loader.py
jamesbot/stock.py
jamesbot/test.py
jamesbot/yahoo_api.py
jamesbot-0.1.2.dist-info/LICENSE
jamesbot-0.1.2.dist-info/METADATA
jamesbot-0.1.2.dist-info/WHEEL
jamesbot-0.1.2.dist-info/top_level.txt
jamesbot-0.1.2.dist-info/RECORD
