Metadata-Version: 2.1
Name: jamesbot
Version: 0.1.2
Summary: Download and Store financial data.
Home-page: https://github.com/felipe-fp/JamesBot
Author: Faruk Hammoud, Felipe Freire Pinto
Author-email: farukhammoud@student-cs.fr, felipe.fp@student-cs.fr
License: UNKNOWN
Platform: UNKNOWN
Classifier: Programming Language :: Python :: 3
Classifier: License :: OSI Approved :: MIT License
Classifier: Operating System :: OS Independent
Requires-Python: >=3.6
Requires-Dist: pandas
Requires-Dist: datetime
Requires-Dist: yfinance
Requires-Dist: xbbg
Requires-Dist: ruamel.yaml
